django_adminlte/__init__.py
django_adminlte/welcom.py
django_adminlte-1.1.dist-info/METADATA
django_adminlte-1.1.dist-info/WHEEL
django_adminlte-1.1.dist-info/top_level.txt
django_adminlte-1.1.dist-info/RECORD
