Metadata-Version: 2.1
Name: django-adminlte
Version: 1.1
Summary: ReUP django-adminlte
Home-page: https://github.com/hpduongducnhan/django-adminlte-reup
Author: hpduongducnhan
Author-email: hpduongducnhan@gmail.com
Maintainer: hpduongducnhan
Maintainer-email: hpduongducnhan@gmail.com
License: MIT
Download-URL: https://github.com/hpduongducnhan/django-adminlte-reup/tarball/master
Platform: UNKNOWN
Classifier: Development Status :: 4 - Beta
Classifier: License :: OSI Approved :: MIT License
Classifier: Topic :: Software Development :: Libraries :: Python Modules
Classifier: Intended Audience :: Developers
Classifier: Programming Language :: Python :: 2
Requires-Python: <3
